paralegal/__init__.py
paralegal-0.1.0.dist-info/METADATA
paralegal-0.1.0.dist-info/WHEEL
paralegal-0.1.0.dist-info/top_level.txt
paralegal-0.1.0.dist-info/RECORD
